decimal_mask/__init__.py
decimal_mask/apps.py
decimal_mask/static/decimal_mask/DecimalMask.js
decimal_mask/static/decimal_mask/init.js
decimal_mask/widgets.py
coral_decimal_mask-0.4.1.dist-info/METADATA
coral_decimal_mask-0.4.1.dist-info/WHEEL
coral_decimal_mask-0.4.1.dist-info/RECORD
